Metadata-Version: 1.1
Name: escea
Version: 2.0.1
Summary: Escea Fireplace API Client
Home-page: http://mal.co.nz
Author: Mal Curtis
Author-email: mal@mal.co.nz
License: 
